MANIFEST.in
README.md
VERSION
requirements.txt
setup.cfg
setup.py
rhasspy_asr_deepspeech_hermes.egg-info/PKG-INFO
rhasspy_asr_deepspeech_hermes.egg-info/SOURCES.txt
rhasspy_asr_deepspeech_hermes.egg-info/dependency_links.txt
rhasspy_asr_deepspeech_hermes.egg-info/entry_points.txt
rhasspy_asr_deepspeech_hermes.egg-info/requires.txt
rhasspy_asr_deepspeech_hermes.egg-info/top_level.txt
rhasspyasr_deepspeech_hermes/__init__.py
rhasspyasr_deepspeech_hermes/__main__.py